pytutils/__init__.py
pytutils/debug.py
pytutils/files.py
pytutils/iters.py
pytutils/log.py
pytutils/mappings.py
pytutils/memo.py
pytutils/meth.py
pytutils/path.py
pytutils/pretty.py
pytutils/props.py
pytutils/python.py
pytutils/pythree.py
pytutils/queues.py
pytutils/rand.py
pytutils/sets.py
pytutils/timers.py
pytutils/tlds.py
pytutils/trees.py
pytutils/urls.py
pytutils/lazy/__init__.py
pytutils/lazy/lazy_import.py
pytutils/lazy/lazy_regex.py
pytutils/lazy/simple_import.py
pytutils-0.1.0.dist-info/AUTHORS
pytutils-0.1.0.dist-info/LICENSE.md
pytutils-0.1.0.dist-info/METADATA
pytutils-0.1.0.dist-info/WHEEL
pytutils-0.1.0.dist-info/pbr.json
pytutils-0.1.0.dist-info/top_level.txt
pytutils-0.1.0.dist-info/RECORD
