Metadata-Version: 1.1
Name: pytutils
Version: 0.1.0
Summary: Heap of garbage from trevorj
Home-page: https://github.com/akatrevorjay/pytutils
Author: Trevor Joynson
Author-email: github@skywww.net
License: GPL
Keywords: python
Platform: UNKNOWN
Classifier: Development Status :: 5 - Production/Stable
Classifier: Intended Audience :: Developers
Classifier: Intended Audience :: Information Technology
Classifier: License :: OSI Approved :: GNU General Public License (GPL)
Classifier: Operating System :: OS Independent
Classifier: Programming Language :: Python
Classifier: Topic :: Software Development
Classifier: Topic :: Software Development :: Libraries
